setup.py
zipgun/__init__.py
zipgun/zipgun.py
zipgun.egg-info/PKG-INFO
zipgun.egg-info/SOURCES.txt
zipgun.egg-info/dependency_links.txt
zipgun.egg-info/requires.txt
zipgun.egg-info/top_level.txt
zipgun/scripts/__init__.py
zipgun/scripts/download_data.py
zipgun/scripts/generate_db.py