Metadata-Version: 1.1
Name: zipgun
Version: 0.3.0
Summary: Postal code library for Python
Home-page: http://github.com/msherry/zipgun
Author: Marc Sherry
Author-email: msherry@gmail.com
License: UNKNOWN
Platform: UNKNOWN
Classifier: Intended Audience :: Developers
Classifier: Development Status :: 4 - Beta
Classifier: Natural Language :: English
Classifier: Topic :: Software Development :: Libraries :: Python Modules
Classifier: License :: OSI Approved :: Apache Software License
Classifier: Programming Language :: Python
Classifier: Programming Language :: Python :: 2.7
